quasinet/__init__.py
quasinet/_config.py
quasinet/_encoders.py
quasinet/_qnet_utils.pyx
quasinet/ciforest.py
quasinet/citrees.py
quasinet/curvature.py
quasinet/export.py
quasinet/feature_importance.py
quasinet/feature_selectors.py
quasinet/metrics.py
quasinet/osfix.py
quasinet/qnet.py
quasinet/qsampling.py
quasinet/qseqtools.py
quasinet/scorers.py
quasinet/tree.py
quasinet/utils.py
quasinet/zqnet.py
quasinet/bin/Cfunc.so
quasinet/bin/dcor.so
quasinet/bin/mac_dcor.so
quasinet/bin/macnew_Cfunc.so
quasinet/bin/macnew_dcor.so
quasinet/bin/macx86_Cfunc.so
quasinet/bin/macx86_dcor.so
quasinet/bin/win_Cfunc.so
quasinet/bin/win_dcor.so
quasinet/qnet_trees/coronavirus/bat.joblib
quasinet/qnet_trees/coronavirus/covid19.joblib
quasinet/qnet_trees/coronavirus/game.joblib
quasinet/qnet_trees/coronavirus/rat.joblib
quasinet/qnet_trees/influenza/h1n1humanHA/2000_2001.joblib
quasinet/qnet_trees/influenza/h1n1humanHA/2001_2002.joblib
quasinet/qnet_trees/influenza/h1n1humanHA/2003_2004.joblib
quasinet/qnet_trees/influenza/h1n1humanHA/2005_2006.joblib
quasinet/qnet_trees/influenza/h1n1humanHA/2006_2007.joblib
quasinet/qnet_trees/influenza/h1n1humanHA/2007_2008.joblib
quasinet/qnet_trees/influenza/h1n1humanHA/2008_2009.joblib
quasinet/qnet_trees/influenza/h1n1humanHA/2009_2010.joblib
quasinet/qnet_trees/influenza/h1n1humanHA/2010_2011.joblib
quasinet/qnet_trees/influenza/h1n1humanHA/2011_2012.joblib
quasinet/qnet_trees/influenza/h1n1humanHA/2012_2013.joblib
quasinet/qnet_trees/influenza/h1n1humanHA/2013_2014.joblib
quasinet/qnet_trees/influenza/h1n1humanHA/2014_2015.joblib
quasinet/qnet_trees/influenza/h1n1humanHA/2015_2016.joblib
quasinet/qnet_trees/influenza/h1n1humanHA/2016_2017.joblib
quasinet/qnet_trees/influenza/h1n1humanHA/2017_2018.joblib
quasinet/qnet_trees/influenza/h1n1humanHA/2018_2019.joblib
quasinet/qnet_trees/influenza/h1n1humanHA/2019_2020.joblib
quasinet/qnet_trees/influenza/h1n1humanNA/2000_2001.joblib
quasinet/qnet_trees/influenza/h1n1humanNA/2001_2002.joblib
quasinet-0.1.76.dist-info/LICENSE
quasinet-0.1.76.dist-info/METADATA
quasinet-0.1.76.dist-info/WHEEL
quasinet-0.1.76.dist-info/top_level.txt
quasinet-0.1.76.dist-info/RECORD
