Metadata-Version: 2.1
Name: quasinet
Version: 0.1.76
Summary: Utitilies for constructing and manipulating models for non-local structural dependencies in genomic sequences
Home-page: https://github.com/zeroknowledgediscovery/
Download-URL: https://github.com/zeroknowledgediscovery/quasinet/archive/0.1.76.tar.gz
Author: zed.uchicago.edu
Author-email: ishanu@uchicago.edu
License: LICENSE.txt
Keywords: decision trees,machine learning,computational biology
Classifier: Development Status :: 4 - Beta
Classifier: Intended Audience :: Developers
Classifier: Intended Audience :: Science/Research
Classifier: Topic :: Scientific/Engineering :: Information Analysis
Classifier: Topic :: Scientific/Engineering :: Bio-Informatics
Classifier: Topic :: Software Development :: Libraries
Classifier: License :: OSI Approved :: MIT License
Classifier: Programming Language :: Python :: 3.3
Requires-Python: >=3.3
License-File: LICENSE
Requires-Dist: scikit-learn
Requires-Dist: scipy
Requires-Dist: numpy
Requires-Dist: numba
Requires-Dist: pandas
Requires-Dist: joblib
Requires-Dist: dill
